promptgear/__init__.py
promptgear/cli.py
promptgear/config.py
promptgear/core.py
promptgear/filesystem_backend.py
promptgear/manager.py
promptgear/postgres_backend.py
promptgear/schema.py
promptgear/sqlite_backend.py
promptgear/yaml_utils.py
prompt_gear-0.1.0b2.dist-info/METADATA
prompt_gear-0.1.0b2.dist-info/WHEEL
prompt_gear-0.1.0b2.dist-info/entry_points.txt
prompt_gear-0.1.0b2.dist-info/licenses/LICENSE
prompt_gear-0.1.0b2.dist-info/RECORD
