Metadata-Version: 2.4
Name: prompt-gear
Version: 0.1.0b2
Summary: YAML-powered prompt manager with multi-backend support
Project-URL: Homepage, https://github.com/miniGears/prompt-gear
Project-URL: Repository, https://github.com/miniGears/prompt-gear
Project-URL: Documentation, https://github.com/miniGears/prompt-gear#readme
Project-URL: Issues, https://github.com/miniGears/prompt-gear/issues
Author-email: miniGears <wenyi@wygears.com>
License: MIT
License-File: LICENSE
Keywords: AI,LLM,management,prompt,template
Classifier: Development Status :: 4 - Beta
Classifier: Intended Audience :: Developers
Classifier: License :: OSI Approved :: MIT License
Classifier: Programming Language :: Python :: 3
Classifier: Programming Language :: Python :: 3.9
Classifier: Programming Language :: Python :: 3.10
Classifier: Programming Language :: Python :: 3.11
Classifier: Programming Language :: Python :: 3.12
Classifier: Topic :: Software Development :: Libraries :: Python Modules
Requires-Python: >=3.9
Requires-Dist: pydantic>=2.0.0
Requires-Dist: python-dotenv>=1.0.0
Requires-Dist: rich>=13.0.0
Requires-Dist: ruamel-yaml>=0.18.0
Requires-Dist: typer>=0.9.0
Provides-Extra: dev
Requires-Dist: black>=23.0.0; extra == 'dev'
Requires-Dist: flake8>=7.2.0; extra == 'dev'
Requires-Dist: mypy>=1.0.0; extra == 'dev'
Requires-Dist: pytest-cov>=4.0.0; extra == 'dev'
Requires-Dist: pytest>=7.0.0; extra == 'dev'
Provides-Extra: postgres
Requires-Dist: psycopg2-binary>=2.9.0; extra == 'postgres'
Provides-Extra: sqlite
